terragon/__init__.py
terragon/alaska_satellite_facility.py
terragon/base.py
terragon/copernicus_data_space_ecosystem.py
terragon/google_earth_engine.py
terragon/init.py
terragon/microsoft_planetary_computer.py
terragon/utils.py
terragon_downloader-0.3.0.dist-info/licenses/LICENSE
terragon_downloader-0.3.0.dist-info/METADATA
terragon_downloader-0.3.0.dist-info/WHEEL
terragon_downloader-0.3.0.dist-info/top_level.txt
terragon_downloader-0.3.0.dist-info/RECORD
