Metadata-Version: 2.4
Name: terragon-downloader
Version: 0.3.0
Summary: Create EO Minicubes from Polygons and simplify EO Data downloading.
Author-email: Adrian Höhl <adrian.hoehl@tum.de>
License: MIT License
Project-URL: Homepage, https://github.com/drnhhl/terragon
Project-URL: Documentation, https://readthedocs.org
Classifier: Development Status :: 3 - Alpha
Classifier: Intended Audience :: Science/Research
Classifier: License :: OSI Approved :: MIT License
Classifier: Programming Language :: Python :: 3
Classifier: Topic :: Database :: Front-Ends
Classifier: Topic :: Scientific/Engineering :: GIS
Requires-Python: >=3.9
License-File: LICENSE
Requires-Dist: geopandas
Requires-Dist: joblib
Requires-Dist: requests
Requires-Dist: rioxarray
Provides-Extra: gee
Requires-Dist: earthengine-api; extra == "gee"
Requires-Dist: geedim; extra == "gee"
Provides-Extra: pc
Requires-Dist: odc-stac; extra == "pc"
Requires-Dist: planetary-computer; extra == "pc"
Provides-Extra: cdse
Requires-Dist: boto3; extra == "cdse"
Requires-Dist: rasterio>=1.4.0; extra == "cdse"
Provides-Extra: asf
Requires-Dist: asf-search; extra == "asf"
Requires-Dist: remotezip; extra == "asf"
Dynamic: license-file
